bdms/__init__.py
bdms/_version.py
bdms/acada_ingest_cli.py
bdms/acada_ingestion.py
bdms/extract_fits_metadata.py
bdms/ingest_tasks.py
bdms/sync_iam_rucio.py
bdms/version.py
bdms/tests/__init__.py
bdms/tests/__main__.py
bdms/tests/conftest.py
bdms/tests/test_acada_ingest_cli.py
bdms/tests/test_acada_ingestion.py
bdms/tests/test_basic_rucio_functionality.py
bdms/tests/test_dpps_rel_0_0.py
bdms/tests/test_extract_fits_metadata.py
bdms/tests/test_file_replicas.py
bdms/tests/test_iam.py
bdms/tests/test_metadata.py
bdms/tests/test_onsite_storage.py
bdms/tests/test_prod.py
bdms/tests/test_rucio_with_iam_sync_user.py
bdms/tests/test_unit_iam_sync_user.py
bdms/tests/utils.py
ctao_bdms_clients-0.6.0.dist-info/licenses/LICENSE
ctao_bdms_clients-0.6.0.dist-info/METADATA
ctao_bdms_clients-0.6.0.dist-info/WHEEL
ctao_bdms_clients-0.6.0.dist-info/entry_points.txt
ctao_bdms_clients-0.6.0.dist-info/top_level.txt
ctao_bdms_clients-0.6.0.dist-info/RECORD
