Metadata-Version: 2.4
Name: ctao-bdms-clients
Version: 0.6.0
Summary: Client module for the CTAO DPPS Bulk Data Management System
Author-email: Georgios Zacharis <georgios.zacharis@inaf.it>, Stefano Gallozzi <Stefano.gallozzi@inaf.it>, Michele Mastropietro <michele.mastropietro@inaf.it>, Syed Anwar Ul Hasan <syedanwarul.hasan@cta-consortium.org>, Maximilian Linhoff <maximilian.linhoff@cta-observatory.org>, Volodymyr Savchenko <Volodymyr.Savchenko@epfl.ch>, Frederic Gillardo <gilllardo@lapp.in2p3.fr>
License-Expression: BSD-3-Clause
Project-URL: repository, https://gitlab.cta-observatory.org/cta-computing/dpps/bdms/bdms
Project-URL: documentation, http://cta-computing.gitlab-pages.cta-observatory.org/dpps/bdms/bdms
Requires-Python: >=3.9
License-File: LICENSE
Requires-Dist: astropy<8.0.0,>=6.0.1
Requires-Dist: ctao-bdms-rucio-policy~=0.2.0
Requires-Dist: rucio-clients~=39.0.0
Requires-Dist: protozfits>=2.7.2
Requires-Dist: watchdog>=6.0.0
Requires-Dist: filelock>=3.18.0
Requires-Dist: prometheus-client>=0.22.1
Requires-Dist: ruamel.yaml
Requires-Dist: celery>=5.5.0
Requires-Dist: redis>=6.0.0
Provides-Extra: test
Requires-Dist: pytest; extra == "test"
Requires-Dist: pytest-cov; extra == "test"
Requires-Dist: pytest-requirements; extra == "test"
Requires-Dist: python-dotenv; extra == "test"
Requires-Dist: boto3; extra == "test"
Requires-Dist: pytest-xdist; extra == "test"
Provides-Extra: doc
Requires-Dist: sphinx; extra == "doc"
Requires-Dist: numpydoc; extra == "doc"
Requires-Dist: ctao-sphinx-theme; extra == "doc"
Requires-Dist: myst-parser; extra == "doc"
Requires-Dist: sphinx-changelog; extra == "doc"
Requires-Dist: sphinx-automodapi; extra == "doc"
Provides-Extra: dev
Requires-Dist: setuptools_scm; extra == "dev"
Requires-Dist: sphinx-autobuild; extra == "dev"
Provides-Extra: all
Requires-Dist: bdms[dev,doc,test]; extra == "all"
Dynamic: license-file
